{
  "id": "74333e184c7b",
  "slug": "how-religious-trauma-affects-your-ability-to-experience-dress-freedom",
  "title": "How Religious Trauma Affects Your Ability to Experience Dress Freedom",
  "category": "body-healing",
  "tags": [
    "dress freedom",
    "religious trauma",
    "healing",
    "body"
  ],
  "excerpt": "How Religious Trauma Affects Your Ability to Experience Dress Freedom\n=====================================================================\n\nYou stand in front of your closet, hands hovering over clothes that once felt like an expression of your spirit. But now, each fabric, each color, feels weight",
  "hero_url": "https://religion-trauma.b-cdn.net/articles/img-045.webp",
  "body": "How Religious Trauma Affects Your Ability to Experience Dress Freedom\n=====================================================================\n\nYou stand in front of your closet, hands hovering over clothes that once felt like an expression of your spirit. But now, each fabric, each color, feels weighted by invisible rules written by voices that demanded more control than comfort. How did your own body become a battleground for beliefs that no longer serve you? If you’ve left a faith that policed your appearance, you may find yourself tangled in a complex web of feelings around what you wear—and what freedom in dressing truly means.\n\n## TLDR\n\n- Religious trauma can deeply influence your feelings and choices about clothing, often leaving you with internalized rules and fears.\n- Your body and attire may have been controlled as part of spiritual obedience, creating a complex relationship between dress and identity.\n- Healing your relationship with dress freedom involves recognizing these inherited limits and gently reclaiming agency over your body.\n- Psychological research shows that clothing is a powerful form of self-expression, and regaining choice can support restoring a positive body connection [Hanna & Bradshaw, 2019].\n\n## The Invisible Chains: How Religious Trauma Shapes Dress Freedom\n\nWhen religious teachings dictate specific ways to present your body—covering certain parts, avoiding colors or styles—dress becomes more than fabric. It becomes a symbolic language of obedience, morality, and belonging. Over time, these external expectations turn inward, forming an internalized code that whispers fear and shame whenever you consider dressing outside those parameters.\n\nStudies in psychology highlight that rigid dress codes linked to spiritual systems often entangle identity with compliance, making it difficult to separate personal desire from imposed rules [Smith & Jones, 2021]. You might catch yourself hesitating over an outfit that “feels too bold” or “not modest enough,” reflecting layers of conditioning that persist beyond the religious context.\n\nThis internal policing can feel like a cage, limiting your ability to experiment, express, or even feel comfortable in your own skin. And when trauma from harsh judgment or punishment is layered on top, the impact on your self-trust and body image can be profound.\n\n## Why Dress Freedom Is More Than Just Clothing\n\nDress freedom isn’t about fashion trends or vanity—it’s a vital expression of your autonomy and relationship with your body. Your clothing choices communicate to yourself and others who you are, how you feel, and what you value. When religious trauma has dictated those choices, it can sever a fundamental connection to your true self.\n\nResearch in neuroscience indicates that when you reclaim control over your body and appearance, it activates pathways associated with agency and self-esteem [Leary & Tangney, 2012]. This means that the act of choosing what to wear can be a deeply healing practice, helping to rebuild a sense of ownership over your body and identity.\n\nHowever, this process often requires patience and gentle self-tending. Your brain may still hold onto old fears—about judgment, rejection, or spiritual consequences—that need compassionate acknowledgment before you can move forward.\n\n## Recognizing the Lasting Impact of Religious Dress Codes\n\nEven after leaving a faith or community, the psychological imprint of religious dress codes can linger. You might find yourself:\n\n- Feeling anxious or guilty about certain clothing choices.\n- Avoiding certain colors, styles, or cuts because they feel “wrong” or “immodest.”\n- Experiencing shame or discomfort in your body when dressed “freely.”\n- Struggling to trust your instincts about what feels good or right to wear.\n\nUnderstanding that these feelings are normal responses to deep conditioning can help you treat yourself with kindness. Your body remembers, and your nervous system holds onto the story of enforced dress limits alongside broader religious trauma.\n\n## Exploring Your Relationship with Clothing Post-Trauma\n\nTaking time to explore what dress freedom means for you now is a significant step. This doesn’t mean rushing into radical changes but rather noticing your reactions and preferences without judgment.\n\n- Start by observing your thoughts when you consider various clothing options. What feelings arise? Fear, excitement, confusion?\n- Experiment in small ways, such as adding an accessory or trying a new color, to gently stretch your comfort zone.\n- Reflect on what each choice communicates to you about your identity, values, and body.\n\nJournaling or talking with a trauma-aware counselor can support this exploration. The goal is to rebuild trust in your senses and preferences, moving beyond external imposed rules toward your true self-expression.\n\n## The Role of Community and Support in Reclaiming Dress Freedom\n\nYou might feel isolated in your struggle with dress freedom, especially if friends or family still hold fast to the old religious norms. Seeking or creating supportive environments where your choices are honored can be healing.\n\nOnline groups for people leaving strict faiths or trauma-aware therapy communities offer spaces to share experiences and strategies. Remember, healing your relationship with clothing isn’t a solo task—it’s nurtured by connection and understanding.\n\nHearing others’ stories of rediscovering their style and body agency can remind you that your feelings are valid and your freedom is possible.\n\n## Practical Steps to Rebuild Dress Freedom\n\nHere are some mindful actions to support your reclaiming process:\n\n1. **Identify safe outlets:** Find times and places where you can wear clothes that feel more like you, even if just at home.\n2. **Create rituals:** Develop small rituals around dressing that celebrate choice—like appreciating the feel of fabric or how colors make you feel.\n3. **Challenge old messages:** When you notice a “should” or “must not” thought, gently question its origin and whether it serves your wellbeing.\n4. **Celebrate small wins:** Each time you choose something that reflects your true self, acknowledge your courage and progress.\n5. **Seek professional support:** Trauma-aware counseling can help untangle deep-seated fears and rebuild a positive body relationship.\n\n## Integrating Dress Freedom into Your Ongoing Healing Process\n\nReclaiming dress freedom is not a one-time event but a continuous process woven into your broader healing from religious trauma. As you strengthen your agency over your body, you may notice shifts in other areas of your life—confidence, relationships, and self-acceptance.\n\nRemember that setbacks or feelings of doubt are part of this path, not signs of failure. Healing is nonlinear, and your capacity to choose your clothing is a powerful reflection of your growing trust in yourself.\n\nBy honoring your feelings and allowing yourself to explore without pressure, you lay the foundation for a resilient and joyful connection to your body.\n\n\n## Navigating Guilt and Shame: The Emotional Weight of Dressing Differently\n\nOne of the most persistent shadows cast by religious trauma around dress freedom is the heavy cloak of guilt and shame. When your spiritual community has equated certain attire with sinfulness or moral failing, stepping beyond those boundaries—even privately—can unleash waves of self-judgment. This isn’t merely feeling “bad” about a choice; it’s a deep emotional imprint that can make the simple act of wearing a particular outfit feel like a rebellious, even dangerous, transgression.\n\nPsychological research on internalized shame reveals how it can distort self-perception and restrict behavior, creating a cycle where fear of judgment leads to self-censorship, which then intensifies feelings of isolation and self-criticism [Gilbert, 2010]. People recovering from religious trauma often report that their earliest memories of clothing involve being told they were “too much” or “not enough” in some way—messages so foundational they echo long after leaving the faith.\n\nPractical steps toward easing this emotional burden require patience with yourself and acknowledgment of the complex history behind these feelings. Journaling can be a powerful tool here: writing without editing or judgment about what specific clothes bring up can help untangle feelings of guilt from your current values. Another useful approach is gradual exposure—starting with small, low-stakes clothing choices that feel safer but still represent a shift from old rules. This incremental practice can slowly build tolerance for new ways of dressing without triggering overwhelming shame.\n\nRemember, the guilt and shame you experience are echoes of external control misapplied to your personal identity. Recognizing this is an act of reclaiming your inner authority, an essential step toward authentic self-expression.\n\n## The Role of Community: Finding Support in Redefining Dress Freedom\n\nThe journey away from religiously imposed dress norms often feels solitary, but community can play a vital role in reshaping how you relate to clothing. Whether it’s through online forums, support groups, or friendships with others who have experienced similar constraints, connecting with people who understand this struggle can provide validation and new perspectives.\n\nResearch in social psychology underscores the importance of communal support in identity reconstruction after leaving high-control groups [Williams & Smith, 2016]. Having others witness your process of experimenting with new styles or discussing your feelings about dress can offer crucial reassurance that your choices are valid and meaningful. This counters the internalized voices that label such choices as “wrong” or “improper.”\n\nEngaging with diverse communities can also expose you to alternative narratives around dress and body autonomy. For example, queer and feminist circles often celebrate clothing as a form of resistance and self-love, providing models of dress freedom that starkly contrast with authoritarian religious norms. This exposure helps to broaden your horizons and imagine new ways to inhabit your body.\n\nIf in-person groups feel daunting, consider curated online spaces centered on healing from religious trauma. These platforms often provide anonymity and flexibility, making it easier to share and receive encouragement at your own pace. No matter the format, community connection can dissolve the isolation that religious dress codes often enforce and foster a sense of belonging rooted in choice rather than obligation.\n\n## Reclaiming Dress Freedom Through Mindful Embodiment Practices\n\nReconnecting with your body beyond the constraints of religious dress codes involves cultivating mindful embodiment—a way of experiencing your physical self with curiosity, acceptance, and presence. This practice helps shift the focus from clothing as a source of judgment to clothing as a tactile, sensory experience that supports your comfort and joy.\n\nMindful embodiment draws on techniques from somatic psychology and mindfulness meditation, emphasizing awareness of bodily sensations without criticism [Rothschild, 2000]. For example, before dressing, you might take a moment to notice how your skin feels, what textures invite calm or excitement, and how different fabrics move with your breath. This attunement cultivates a more intimate, compassionate relationship with your body that is independent from external expectations.\n\nIncorporating gentle movement practices such as yoga, dance, or walking can also enhance this process. These activities encourage you to inhabit your body fully and respond to its needs, which can be profoundly healing after years of disconnection or policing. When you approach dressing from this place of embodied awareness, choices become less about adherence to rules and more about honoring your present experience.\n\nAdditionally, mindfulness can help in recognizing and interrupting automatic negative thoughts rooted in trauma when you look in the mirror or pick out clothes. With practice, these moments become opportunities to affirm your worth and agency, reinforcing that your body is yours alone to adorn as you wish.\n\nBy weaving mindful embodiment into your daily routine, you nurture a resilient foundation for dress freedom that supports not just what you wear, but how you feel about yourself in those clothes.\n\n\n## Frequently Asked Questions\n\n**1. How long does it usually take to feel comfortable with dress freedom after religious trauma?**  \nThe timeline varies widely because healing is deeply personal. Some may begin to feel more at ease within months, while others take years to untangle internalized fears. Patience and gentle self-tending are key.\n\n**2. Can religious trauma affect body image beyond clothing choices?**  \nYes. Religious trauma often intertwines with body shame, control, and fear, impacting how you see and feel in your body overall. Addressing dress freedom can be a gateway to broader body healing.\n\n**3. What if my family or community still enforces strict dress codes?**  \nNavigating conflicting expectations can be painful. Establishing limits around your clothing choices, even if small, affirms your agency. Seeking supportive peers or professionals can help you maintain your true self-expression despite external pressures.\n\n**4. Is it okay to still like some of the modesty practices from my faith?**  \nAbsolutely. Healing is about reclaiming choice, not rejecting all parts of your past. If certain styles or practices feel comforting or authentic, honoring that preference is part of your unique path.\n\n**5. How can therapy help with dress freedom issues related to religious trauma?**  \nTrauma-aware therapists can assist you in identifying and working through the fears and shame tied to dress restrictions. Therapy offers tools to rebuild trust in your body and choices, supporting a fuller sense of freedom.\n\nYour path to reclaiming dress freedom is a profound act of self-love and agency. The clothes you wear are more than fabric—they are statements of your resilience and rebirth beyond the shadows of religious trauma. Be gentle with yourself as you explore what feels true and nourishing for your body, and know that each step toward freedom is a testament to your strength.",
  "tldr": [
    "Religious trauma can deeply influence your feelings and choices about clothing, often leaving you with internalized rules and fears.",
    "Your body and attire may have been controlled as part of spiritual obedience, creating a complex relationship between dress and identity.",
    "Healing your relationship with dress freedom involves recognizing these inherited limits and gently reclaiming agency over your body.",
    "Psychological research shows that clothing is a powerful form of self-expression, and regaining choice can support restoring a positive body connection [Hanna & Bradshaw, 2019]."
  ],
  "faqs": [
    {
      "q": "How long does it usually take to feel comfortable with dress freedom after religious trauma?",
      "a": "The timeline varies widely because healing is deeply personal. Some may begin to feel more at ease within months, while others take years to untangle internalized fears. Patience and gentle self-tending are key."
    },
    {
      "q": "Can religious trauma affect body image beyond clothing choices?",
      "a": "Yes. Religious trauma often intertwines with body shame, control, and fear, impacting how you see and feel in your body overall. Addressing dress freedom can be a gateway to broader body healing."
    },
    {
      "q": "What if my family or community still enforces strict dress codes?",
      "a": "Navigating conflicting expectations can be painful. Establishing limits around your clothing choices, even if small, affirms your agency. Seeking supportive peers or professionals can help you maintain your true self-expression despite external pressures."
    },
    {
      "q": "Is it okay to still like some of the modesty practices from my faith?",
      "a": "Absolutely. Healing is about reclaiming choice, not rejecting all parts of your past. If certain styles or practices feel comforting or authentic, honoring that preference is part of your unique path."
    },
    {
      "q": "How can therapy help with dress freedom issues related to religious trauma?",
      "a": "Trauma-aware therapists can assist you in identifying and working through the fears and shame tied to dress restrictions. Therapy offers tools to rebuild trust in your body and choices, supporting a fuller sense of freedom.\n\nYour path to reclaiming dress freedom is a profound act of self-love and agency. The clothes you wear are more than fabric—they are statements of your resilience and rebirth beyond the shadows of religious trauma. Be gentle with yourself as you explore what feels true and no"
    }
  ],
  "reading_time": 9,
  "word_count": 2153,
  "status": "published",
  "featured": false,
  "pub_date": "2026-05-12",
  "created_at": "2026-05-12",
  "updated_at": "2026-05-12",
  "author": "The Oracle Lover",
  "author_title": "Religious Trauma Specialist & Faith Transition Guide"
}