{
  "id": "cfc048e3afc1",
  "slug": "the-trauma-of-leaving-a-jehovahs-witness-community",
  "title": "The Trauma of Leaving a Jehovah's Witness Community",
  "category": "high-control-groups",
  "tags": [
    "Jehovah's Witnesses",
    "leaving",
    "shunning",
    "recovery"
  ],
  "excerpt": "The Trauma of Leaving a Jehovah's Witness Community\n\n## TLDR  \n- Leaving Jehovah’s Witnesses often involves deep emotional pain due to strict community limits and enforced shunning. - Shunning can sever vital social and familial connections, leading to profound grief and isolation.",
  "hero_url": "https://religion-trauma.b-cdn.net/articles/img-041.webp",
  "body": "The Trauma of Leaving a Jehovah's Witness Community\n\n## TLDR  \n- Leaving Jehovah’s Witnesses often involves deep emotional pain due to strict community limits and enforced shunning.  \n- Shunning can sever vital social and familial connections, leading to profound grief and isolation.  \n- Recovery includes rebuilding your sense of self, processing complex feelings, and finding new supportive connections.  \n- Understanding the psychological impact of high-control groups can help validate your experience and guide your healing process.\n\n## When Leaving Means Losing Everything\n\nImagine standing at the edge of a vast, familiar forest you’ve known your whole life, and suddenly, you must walk away—alone. For many who leave Jehovah’s Witnesses, this isn’t just a metaphor; it’s a harsh reality. The community you trusted, the loved ones you depended on, and the beliefs that shaped your identity can all feel like they crumble at once. This rupture is not simply about changing faith; it’s about losing a world.\n\nLeaving Jehovah’s Witnesses often means more than just saying goodbye to a religion. It can mean being cut off from family members and lifelong friends due to the practice of shunning, a form of social exclusion used to enforce conformity. This experience can trigger deep grief, confusion, and trauma, as your emotional support system is suddenly withdrawn.\n\n## Understanding the Control Within the Community\n\nJehovah’s Witnesses are known for their strict rules and high demands on members’ behavior and beliefs. The community enforces limits on social interactions, dictates acceptable thoughts and actions, and closely monitors adherence to doctrine. Psychologists note that high-control groups often use such mechanisms to maintain authority and conformity, sometimes at the cost of individual autonomy [Lalich & Tobias, 2006].\n\nIn this environment, questioning or doubting the faith is often met with suspicion, accusation, and disciplinary measures. The fear of shunning—a total cutoff from the community—can create intense internal conflict. Many members suppress their doubts and questions to avoid isolation, but when someone decides to leave, the consequences are severe and immediate.\n\n## The Pain of Shunning: More Than Social Rejection\n\nShunning is one of the most traumatic aspects of leaving Jehovah’s Witnesses. It involves deliberately avoiding association with former members, including family, friends, and acquaintances within the community. This social exile is intended as a punishment and a deterrent but often results in profound psychological harm.\n\nResearch on social rejection highlights how critical connections are to human well-being. Being cut off from your social group activates the brain’s pain centers, similar to physical pain [Eisenberger, 2012]. For former Jehovah’s Witnesses, the loss can feel like a death—not just of relationships but of identity and belonging. The isolation can exacerbate feelings of depression, anxiety, and low self-worth, making recovery a complex process.\n\n## Rebuilding After Shunning: The Challenge of Starting Over\n\nWhen you leave a high-control group like Jehovah’s Witnesses, you face the daunting task of rebuilding your life from the ground up. Your previous social networks may no longer be available, and your worldview and skills may have been shaped within a very narrow context. This can leave you feeling unprepared and overwhelmed.\n\nMany who leave experience what therapists call “identity foreclosure,” where their sense of self was heavily invested in the group’s identity, leaving a void after departure [Marcia, 1966]. To recover, you may need to gradually explore and redefine your beliefs, values, and goals outside of the community’s framework. This process requires patience and compassion toward yourself as you rediscover your true self.\n\n## Processing Complex Emotions: Grief, Anger, and Ambivalence\n\nLeaving a Jehovah’s Witness community often stirs a storm of emotions. You may feel grief for the loss of relationships and a familiar way of life. Anger toward the community or individuals who enforced shunning is common and valid. You might also feel ambivalence—simultaneous love and resentment—toward those you left behind.\n\nAcknowledging and allowing yourself to feel these emotions is crucial. Suppressing or rushing through feelings can delay healing and leave unresolved wounds. Therapeutic approaches that cultivate emotional awareness and self-compassion have been shown to facilitate recovery from relational losses [Neff, 2003].\n\n## Finding New Connections and Supportive Environments\n\nOne of the most important steps after leaving Jehovah’s Witnesses is seeking or creating new social connections that honor your true self. New friends, support groups, online communities, or therapists who understand religious trauma can provide the empathy and acceptance you may have been denied.\n\nResearch emphasizes the importance of supportive environments in recovering from social exclusion and identity loss [Haslam et al., 2009]. These communities can help you rebuild trust, develop social skills, and restore a sense of belonging. Remember, finding your tribe outside the faith community is not only possible but essential for your well-being.\n\n## Cultivating Agency: Taking Ownership of Your Path\n\nReclaiming your agency after leaving a controlling group involves making choices that reflect your values and desires rather than imposed doctrines. This may mean exploring new ideas, setting personal limits on what you accept in relationships, and learning to trust your judgment.\n\nPsychological studies show that regaining a sense of control over your life is a key factor in overcoming trauma and building resilience [Bandura, 1997]. While the process can feel slow and uncertain, every step you take to affirm your autonomy strengthens your foundation for a fulfilling life.\n\n## Professional Support: When and How to Seek Help\n\nHealing from the trauma of leaving Jehovah’s Witnesses is often complex and layered. Professional support from therapists experienced in religious trauma or cult recovery can provide guidance, validation, and coping tools. They can help you navigate feelings of loss, identity confusion, and anxiety that may arise.\n\nIt is important to find providers who respect your experience and do not pathologize your background. Trauma-aware approaches focus on your strengths and support your self-tending practices. Remember, seeking help is a brave and valuable act of self-respect.\n\n\n## Rebuilding Identity After Leaving: Who Am I Now?\n\nOne of the most disorienting challenges after leaving a Jehovah’s Witness community is the collapse of the identity you once held. For many, their sense of self was tightly interwoven with the group’s teachings, rituals, and social roles. When that framework disappears, it can feel as if the ground beneath you has vanished. Questions like “Who am I without this?” or “What do I believe now?” are not only common—they are essential.\n\nResearch on identity reconstruction after leaving high-control groups suggests that this process involves both mourning the old self and consciously creating a new one [Palmer & Lalich, 2017]. It’s important to acknowledge that your previous identity was shaped under conditions where autonomy was constrained. This means your new identity can be crafted with greater freedom and authenticity—a daunting, yet hopeful prospect.\n\nPractically, this might mean exploring values and interests that were discouraged or ignored before. It could involve learning about different philosophies, spirituality, or secular worldviews, and seeing what resonates with your lived experience and intuitive sense of meaning. Journaling can be a powerful tool here, allowing you to articulate shifting beliefs and feelings without judgment.\n\nIt’s also vital to be patient with yourself. Identity reconstruction is not linear or quick. You may oscillate between despair and hope, certainty and confusion. Seeking out communities or individuals who respect your evolving beliefs without pressure can provide mirrors for your emerging self. Remember, rebuilding your identity is not about “fixing” something broken but about rediscovering the fullness of your humanity beyond imposed limits.\n\n## Navigating Family Dynamics Post-Departure\n\nFamily relationships after leaving Jehovah’s Witnesses are often some of the most complex and emotionally charged aspects of this experience. Because shunning policies can extend to immediate family, many who leave are faced with estrangement from parents, siblings, or children. The grief of losing family connection is profound and can feel like an unbearable betrayal.\n\nIt’s important to recognize the dual reality here: your family members are often acting from the framework they have been taught, which includes fear and loyalty to the organization. Their rejection, while painful, is usually rooted in their own conditioning, not personal spite. This understanding doesn’t lessen your pain but can help temper feelings of internalized blame or anger.\n\nCommunication with family post-departure requires careful navigation. Some former members find that limited, non-religious contact—when possible—is a way to maintain some connection without reopening wounds. Others may find that no contact is necessary to preserve mental and emotional health. The decision is deeply personal and situational.\n\nTherapeutic support can be invaluable here. Therapists who understand religious disaffiliation can help you process complex emotions like grief, resentment, guilt, or hope. They can also assist in developing coping strategies to handle family interactions or the absence of them. Remember, the loss of family ties is a profound form of mourning, and allowing yourself to grieve fully is a crucial step toward emotional well-being.\n\n## Finding New Communities and Support Systems\n\nAfter leaving a Jehovah’s Witness community, many people face a daunting social reality: the absence of a ready-made community. Because the original group provided not only spiritual guidance but social structure, fellowship, and shared purpose, its loss can leave a void that feels impossible to fill.\n\nBuilding new connections takes time and intention. It’s helpful to seek out groups or individuals who offer acceptance without judgment or doctrine. This might include secular communities, spiritual groups that encourage questioning, or support networks specifically for former members of high-control groups.\n\nOnline forums and social media groups can be a good starting point, offering anonymity and a sense of camaraderie with others who understand the unique challenges of leaving Jehovah’s Witnesses. However, in-person connections often provide deeper emotional nourishment, so exploring local meetups, interest-based clubs, or volunteer opportunities can create meaningful bonds.\n\nDeveloping friendships outside the former community also means learning new social skills, especially if your previous environment discouraged certain types of interaction. Being open to curiosity and vulnerability can foster authentic connections, even if the process feels slow or awkward at times.\n\nUltimately, cultivating relationships grounded in mutual respect and freedom helps restore a sense of belonging and counters the isolation left by shunning. Remember that you are not alone; many have walked this path before, and finding others who recognize your experience can be a powerful balm for the heart and soul.\n\n\n## Frequently Asked Questions\n\n**1. Why do Jehovah’s Witnesses practice shunning, and how does it affect those who leave?**  \nShunning is used as a disciplinary measure to enforce adherence to the faith’s rules. It involves cutting off social and familial contact with those who leave or dissent. This can cause deep emotional pain, feelings of abandonment, and isolation, complicating the process of leaving and recovery.\n\n**2. How long does the recovery process take after leaving Jehovah’s Witnesses?**  \nThere is no set timeline for recovery. Healing from the loss and trauma of leaving a high-control group can take months or years, depending on individual circumstances, support systems, and personal resilience. Patience and self-compassion are essential throughout this process.\n\n**3. Can former Jehovah’s Witnesses repair relationships with family members who shun them?**  \nReconciliation is sometimes possible, but it depends on the willingness of both parties and changes in community rules or personal beliefs. Many experience ongoing rejection, so it’s important to prepare for various outcomes and focus on building new supportive relationships.\n\n**4. What are some signs that professional help might be needed?**  \nIf feelings of depression, anxiety, or isolation become overwhelming or interfere with daily functioning, seeking professional support is advisable. Therapy can provide tools to process trauma, rebuild identity, and cope with emotional challenges.\n\n**5. How can I find others who have left Jehovah’s Witnesses for support?**  \nOnline forums, social media groups, and local meetups for former members can offer connection and understanding. Look for trauma-aware communities where your experience is respected, and you can share without judgment.\n\nLeaving a Jehovah’s Witness community is undeniably difficult, marked by loss and upheaval that touches every part of your life. But through the pain and confusion, there is room for growth and rediscovery. You deserve compassion for the courage it takes to step away, and you are not alone. With time, support, and kindness toward yourself, you can build a life grounded in your truth and surrounded by those who respect and cherish you for who you truly are.",
  "tldr": [],
  "faqs": [
    {
      "q": "Why do Jehovah’s Witnesses practice shunning, and how does it affect those who leave?",
      "a": "Shunning is used as a disciplinary measure to enforce adherence to the faith’s rules. It involves cutting off social and familial contact with those who leave or dissent. This can cause deep emotional pain, feelings of abandonment, and isolation, complicating the process of leaving and recovery."
    },
    {
      "q": "How long does the recovery process take after leaving Jehovah’s Witnesses?",
      "a": "There is no set timeline for recovery. Healing from the loss and trauma of leaving a high-control group can take months or years, depending on individual circumstances, support systems, and personal resilience. Patience and self-compassion are essential throughout this process."
    },
    {
      "q": "Can former Jehovah’s Witnesses repair relationships with family members who shun them?",
      "a": "Reconciliation is sometimes possible, but it depends on the willingness of both parties and changes in community rules or personal beliefs. Many experience ongoing rejection, so it’s important to prepare for various outcomes and focus on building new supportive relationships."
    },
    {
      "q": "What are some signs that professional help might be needed?",
      "a": "If feelings of depression, anxiety, or isolation become overwhelming or interfere with daily functioning, seeking professional support is advisable. Therapy can provide tools to process trauma, rebuild identity, and cope with emotional challenges."
    },
    {
      "q": "How can I find others who have left Jehovah’s Witnesses for support?",
      "a": "Online forums, social media groups, and local meetups for former members can offer connection and understanding. Look for trauma-aware communities where your experience is respected, and you can share without judgment.\n\nLeaving a Jehovah’s Witness community is undeniably difficult, marked by loss and upheaval that touches every part of your life. But through the pain and confusion, there is room for growth and rediscovery. You deserve compassion for the courage it takes to step away, and you are"
    }
  ],
  "reading_time": 9,
  "word_count": 2037,
  "status": "published",
  "featured": false,
  "pub_date": "2026-12-16",
  "created_at": "2026-12-16",
  "updated_at": "2026-12-16",
  "author": "The Oracle Lover",
  "author_title": "Religious Trauma Specialist & Faith Transition Guide"
}