{
  "id": "bacee6984440",
  "slug": "what-is-spiritual-abuse-a-clinical-definition",
  "title": "What Is Spiritual Abuse? A Clinical Definition",
  "category": "religious-trauma",
  "tags": [
    "spiritual abuse",
    "definition",
    "clinical",
    "recognition"
  ],
  "excerpt": "What Is Spiritual Abuse? A Clinical Definition\n\nHave you ever felt deep confusion or pain after experiences within your religious community—moments when faith was used not to uplift but to control, shame, or silence you?",
  "hero_url": "https://religion-trauma.b-cdn.net/article-rts.webp",
  "body": "What Is Spiritual Abuse? A Clinical Definition\n\nHave you ever felt deep confusion or pain after experiences within your religious community—moments when faith was used not to uplift but to control, shame, or silence you? If so, you may have encountered spiritual abuse, a form of harm that often hides behind the language of faith and trust. Understanding what spiritual abuse really means, especially from a clinical perspective, can be a vital step toward reclaiming your sense of self and beginning a healing process.\n\n## TLDR\n\n- Spiritual abuse involves the misuse of religious or spiritual authority to control, manipulate, or harm another person emotionally, psychologically, or physically.\n- Clinically, spiritual abuse is recognized as a form of emotional abuse, often involving coercion, shaming, and exploitation within a faith context.\n- Symptoms can include confusion about personal identity, guilt, anxiety, and difficulty trusting others or spirituality itself.\n- Awareness and recognition of spiritual abuse are essential for recovery; professional support from trauma-aware therapists can help navigate these complex wounds.\n\n## Defining Spiritual Abuse: More Than Just Bad Religion\n\nSpiritual abuse is often described as the misuse of spiritual authority or power to harm others. Unlike physical abuse, it’s less visible, making it harder to identify and name. It can appear as manipulation, control, shaming, or silencing under the guise of religious dogma or spiritual “truths.” Clinically, spiritual abuse is not a standalone diagnosis but is recognized within the framework of emotional and psychological abuse, often intertwined with coercive control (Bergin & Jensen, 1990).\n\nThis form of abuse exploits the deep trust people place in spiritual leaders or communities, making victims doubly vulnerable. The abuser may impose rigid rules, demand unquestioning obedience, or use fear of divine punishment to maintain control. This can severely damage your sense of agency and your connection to your own spirituality.\n\n## Clinical Perspectives: How Mental Health Professionals See Spiritual Abuse\n\nMental health professionals approach spiritual abuse as a form of emotional maltreatment occurring within a religious or spiritual context. It shares many features with psychological abuse, such as gaslighting, manipulation, and intimidation, but is unique because it weaponizes spirituality itself (Richards & Bergin, 2005).\n\nClinicians recognize that spiritual abuse can lead to complex trauma responses. The victim may struggle with guilt, shame, chronic anxiety, depression, or post-traumatic stress symptoms. Because spiritual beliefs are often core to identity, abuse in this area can disrupt your understanding of yourself and your place in the world. This is why recovery often requires addressing both psychological wounds and spiritual confusion.\n\n## Common Signs and Symptoms of Spiritual Abuse\n\nIf you’re wondering whether what you’ve experienced fits the definition of spiritual abuse, here are some signs to consider:\n\n- You were punished or shamed for questioning beliefs or leaders.\n- Your personal decisions were overridden by religious authorities.\n- Fear of divine wrath or eternal punishment was used to control your behavior.\n- You were isolated from friends or family who didn’t share your faith.\n- You experienced emotional manipulation in the name of spiritual growth.\n\nThese experiences can leave lasting scars. Research shows that those who face spiritual abuse often report feelings of betrayal, loss of trust, and a fractured sense of self (Wilcox, 2017). You might find it hard to engage with spirituality or relationships afterward, which can feel deeply isolating.\n\n## Why Spiritual Abuse Is Often Overlooked or Minimised\n\nOne reason spiritual abuse is so painful is because it occurs in places where you expect love, support, and acceptance. Religious communities are meant to nurture, not harm, so when abuse happens there, it can be confusing and hard to accept.\n\nAdditionally, spiritual abuse is often minimized by others who do not understand its subtle, insidious nature. Sometimes abusers themselves deny wrongdoing by framing their controlling behavior as “discipline” or “spiritual correction.” This cultural minimization contributes to victims questioning their own reality, which can exacerbate feelings of guilt and shame (Nason-Clark, 2004).\n\nThis minimization is why having a clear, clinical definition is so important: it validates your experience and helps distinguish spiritual abuse from normal religious disagreement or discipline.\n\n## The Intersection of Spiritual Abuse and Coercive Control\n\nSpiritual abuse frequently overlaps with coercive control—a pattern of behaviors used to dominate and isolate someone emotionally and psychologically. Within religious settings, coercive control can take on unique forms, such as enforcing strict adherence to religious laws or isolating individuals from non-believers.\n\nUnderstanding coercive control helps clarify why spiritual abuse is so damaging. It’s not just about harsh rules but about undermining your autonomy and freedom in deeply personal ways. This can lead to learned helplessness, where you feel unable to change your situation or believe that any attempt to resist will lead to greater harm (Stark, 2007).\n\nRecognizing this dynamic is crucial because it highlights the need for careful, trauma-aware support to safely regain your agency.\n\n## Healing Process After Spiritual Abuse: What You Can Expect\n\nRecovering from spiritual abuse is often a slow and non-linear process. Because your spiritual beliefs and identity were involved in the abuse, healing may require rebuilding your trust in yourself and your understanding of spirituality.\n\nTherapists who are trauma-aware and familiar with religious trauma can be invaluable. They can help you explore your experiences, process feelings of betrayal and confusion, and re-establish your limits in future relationships. Research suggests that integrating psychotherapy with spiritual exploration—on your own terms—can significantly reduce symptoms like anxiety and depression (Exline, 2013).\n\nYou might also find it helpful to connect with communities that respect your true self and provide a supportive environment for your healing process.\n\n## How to Recognize Spiritual Abuse in Others and Offer Support\n\nIf someone you love is dealing with spiritual abuse, your awareness can be a lifeline. Look out for signs such as withdrawal, fear about religious gatherings, or expressions of guilt and shame that seem disproportionate.\n\nOffering nonjudgmental listening, validating their feelings, and respecting their pace in sharing can make a profound difference. Avoid dismissing their experience or rushing them to “forgive and move on,” which can mirror the harmful dynamics they faced.\n\nEncouraging professional support and gently helping them explore trauma-aware resources may strengthen their sense of agency. Remember, your role is to be a compassionate witness, not a fixer.\n\n\n## The Long-Term Impact of Spiritual Abuse on Identity and Relationships\n\nSpiritual abuse can leave deep and lasting scars that extend far beyond the immediate context of the religious community in which it occurred. Because spirituality often forms the foundation of a person’s identity and worldview, when that foundation is shaken by abuse, the effects can ripple into many areas of life. Survivors frequently report a profound sense of lost or fragmented identity. You might find yourself questioning who you are without the religious framework that once defined your values, purpose, and belonging.\n\nThis identity disruption often manifests as a persistent internal conflict: a longing for connection to spirituality coupled with fear or mistrust of it. It’s not uncommon to feel alienated from both your former faith community and from broader social networks that share similar beliefs. Relationships can become complicated, as spiritual abuse can undermine your ability to trust others, especially authority figures or those who represent the faith you were taught to revere.\n\nMoreover, survivors sometimes struggle with perfectionism or hyper-vigilance, conditioned by years of rigid spiritual expectations or fear of divine punishment. This internalized pressure can lead to chronic anxiety and self-criticism, making it difficult to develop healthy, nurturing relationships. Intimacy may be compromised by fears of being controlled or judged.\n\nIt’s important to recognize that these long-term effects are not a sign of personal weakness or failure. They are a natural response to profound emotional and spiritual injury. Healing involves creating new ways to understand yourself, reconstruct your identity outside of imposed doctrines, and develop relational trust on your own terms.\n\n## Navigating Recovery: Rebuilding Trust in Yourself and Your Spirituality\n\nRecovering from spiritual abuse requires more than just distancing yourself from harmful environments—it involves actively reclaiming your personal authority over your beliefs and values. This process can be daunting when the language of faith has been used to control or silence you, but it’s essential for rebuilding a sense of autonomy and inner peace.\n\nA helpful first step is to give yourself permission to question and explore, without judgment or pressure to arrive at immediate answers. This might involve reading widely from multiple spiritual perspectives, engaging with supportive communities that respect your journey, or simply allowing space for doubt and curiosity. Remember, spirituality is not a fixed destination; it’s a deeply personal landscape that can be reshaped in ways that honor your experience.\n\nProfessional support from therapists who understand the nuances of religious trauma can be invaluable. Such professionals can help you untangle the intertwined threads of emotional pain and spiritual confusion, guiding you toward self-compassion and clarity. Techniques drawn from trauma therapy—like grounding exercises, cognitive restructuring, or narrative approaches—can support you in reclaiming your story and sense of self.\n\nRebuilding trust also includes learning to listen to your intuition and inner values rather than external demands. This might mean setting firm limits on interactions with former abusers or communities, or redefining what spirituality means to you on your own terms. Over time, many survivors find that they can reconnect with spirituality in a way that is life-affirming, liberating, and deeply healing.\n\n## The Role of Community and Connection in Healing from Spiritual Abuse\n\nWhile spiritual abuse often isolates you, connection with others plays a crucial role in recovery. Finding or creating communities where your experiences are acknowledged and validated can be profoundly restorative. This doesn’t necessarily mean returning to organized religion; rather, it means cultivating relationships that respect your autonomy and offer genuine empathy.\n\nSupport groups specifically for survivors of religious or spiritual abuse can provide a unique space to share your story without fear of judgment. Hearing others’ experiences can help you feel less alone and undermine the internalized shame that abuse often fosters. In these groups, you can practice expressing your truth and receive compassionate feedback, which can rebuild your social confidence and trust.\n\nOutside of formal support groups, nurturing friendships with people who honor your boundaries and encourage authenticity is vital. These connections model healthy relational dynamics and can remind you that faith and spirituality do not have to be instruments of harm or control.\n\nEngaging in creative or contemplative practices—such as journaling, meditation, art, or nature immersion—within supportive communities can also foster healing. These activities allow you to reconnect with your inner life at your own pace, often revealing new sources of meaning and spiritual nourishment.\n\nUltimately, healing from spiritual abuse is not something you must do in isolation. Community, when experienced with safety and respect, offers a powerful counterbalance to the loneliness and disconnection that spiritual abuse often imposes. It invites you to remember that you are seen, heard, and valued exactly as you are.\n\n\n## Frequently Asked Questions\n\n**1. What exactly qualifies as spiritual abuse?**  \nSpiritual abuse involves using religious or spiritual authority to control, manipulate, shame, or harm another person. It goes beyond normal religious discipline by causing emotional or psychological harm, often through coercion or exploitation of faith.\n\n**2. Can spiritual abuse happen in any religion or spiritual practice?**  \nYes. Spiritual abuse is not limited to any one faith tradition. It can occur in any religious or spiritual community where power is misused to harm others.\n\n**3. How is spiritual abuse different from normal religious disagreements?**  \nNormal disagreements involve differing beliefs or interpretations and usually respect personal agency. Spiritual abuse involves coercion, control, and emotional harm, often silencing dissent and punishing questioning.\n\n**4. What mental health effects can spiritual abuse cause?**  \nIt can lead to anxiety, depression, post-traumatic stress symptoms, loss of trust, confusion about identity, and difficulty in future relationships or spiritual engagement.\n\n**5. How can someone start healing from spiritual abuse?**  \nSeeking support from trauma-aware therapists, connecting with validating communities, and allowing yourself to explore spirituality on your own terms are important steps in the healing process.\n\nYou have endured a unique kind of pain—one wrapped in faith and trust that should have been your refuge. Recognizing spiritual abuse for what it is can be profoundly unsettling, yet it is also a courageous act of reclaiming your story. You deserve to move forward with honesty, respect, and the freedom to shape your spirituality in a way that nourishes your true self. Remember, healing your wounds from spiritual abuse is possible, and there are compassionate guides ready to walk alongside you as you navigate this path.",
  "tldr": [
    "Spiritual abuse involves the misuse of religious or spiritual authority to control, manipulate, or harm another person emotionally, psychologically, or physically.",
    "Clinically, spiritual abuse is recognized as a form of emotional abuse, often involving coercion, shaming, and exploitation within a faith context.",
    "Symptoms can include confusion about personal identity, guilt, anxiety, and difficulty trusting others or spirituality itself.",
    "Awareness and recognition of spiritual abuse are essential for recovery; professional support from trauma-aware therapists can help navigate these complex wounds."
  ],
  "faqs": [
    {
      "q": "What exactly qualifies as spiritual abuse?",
      "a": "Spiritual abuse involves using religious or spiritual authority to control, manipulate, shame, or harm another person. It goes beyond normal religious discipline by causing emotional or psychological harm, often through coercion or exploitation of faith."
    },
    {
      "q": "Can spiritual abuse happen in any religion or spiritual practice?",
      "a": "Yes. Spiritual abuse is not limited to any one faith tradition. It can occur in any religious or spiritual community where power is misused to harm others."
    },
    {
      "q": "How is spiritual abuse different from normal religious disagreements?",
      "a": "Normal disagreements involve differing beliefs or interpretations and usually respect personal agency. Spiritual abuse involves coercion, control, and emotional harm, often silencing dissent and punishing questioning."
    },
    {
      "q": "What mental health effects can spiritual abuse cause?",
      "a": "It can lead to anxiety, depression, post-traumatic stress symptoms, loss of trust, confusion about identity, and difficulty in future relationships or spiritual engagement."
    },
    {
      "q": "How can someone start healing from spiritual abuse?",
      "a": "Seeking support from trauma-aware therapists, connecting with validating communities, and allowing yourself to explore spirituality on your own terms are important steps in the healing process.\n\nYou have endured a unique kind of pain—one wrapped in faith and trust that should have been your refuge. Recognizing spiritual abuse for what it is can be profoundly unsettling, yet it is also a courageous act of reclaiming your story. You deserve to move forward with honesty, respect, and the freedom to"
    }
  ],
  "reading_time": 9,
  "word_count": 2090,
  "status": "published",
  "featured": false,
  "pub_date": "2027-04-29",
  "created_at": "2027-04-29",
  "updated_at": "2027-04-29",
  "author": "The Oracle Lover",
  "author_title": "Religious Trauma Specialist & Faith Transition Guide"
}