{
  "id": "ae38aa215804",
  "slug": "what-is-the-difference-between-religious-trauma-and-coercive-control",
  "title": "What Is the Difference Between Religious Trauma and Coercive Control?",
  "category": "religious-trauma",
  "tags": [
    "coercive control",
    "religious trauma",
    "difference",
    "healing"
  ],
  "excerpt": "What Is the Difference Between Religious Trauma and Coercive Control? =======================================================================\n\nYou might feel trapped between the invisible walls of faith and manipulation, wondering: \"Is what I’m experiencing religious trauma, coercive control, or bot",
  "hero_url": "https://religion-trauma.b-cdn.net/article-rts.webp",
  "body": "What Is the Difference Between Religious Trauma and Coercive Control?\n=======================================================================\n\nYou might feel trapped between the invisible walls of faith and manipulation, wondering: \"Is what I’m experiencing religious trauma, coercive control, or both?\" Many people navigating painful religious experiences find themselves caught in this very confusion, grappling with complex feelings of betrayal, fear, and loss. Understanding the difference between religious trauma and coercive control is not just academic—it is a vital step toward reclaiming your agency and beginning your healing process.\n\n## TLDR\n\n- Religious trauma stems from harmful experiences related to faith and spiritual beliefs, including shame, fear, and spiritual abuse.\n- Coercive control is a pattern of manipulative behaviors intended to dominate and isolate, often used in abusive relationships, including some religious settings.\n- While coercive control can be a component of religious trauma, not all religious trauma involves coercive control.\n- Recognizing these distinctions can help you find the right support and strategies for your healing process.\n\n## Defining Religious Trauma: When Faith Hurts\n\nReligious trauma occurs when your spiritual beliefs or community cause significant psychological, emotional, or spiritual harm. This harm might manifest as deep shame, chronic anxiety around divine judgment, or fear of ostracization. It often involves experiences like spiritual abuse, rigid dogma, or punishment-based teachings that leave you feeling unsafe in your faith.\n\nYou might have been taught that your thoughts or feelings are sinful or that doubt equals eternal condemnation. Such messages can severely undermine your sense of self-worth and trust in your intuition. According to research, religious trauma can lead to symptoms similar to post-traumatic stress disorder, including flashbacks, nightmares, and hypervigilance, especially when the religion involves strict control over personal identity and autonomy [Exline et al., 2014].\n\nThis trauma is not about faith itself but about how faith was imposed or weaponized against you. It often leaves you questioning your identity and spirituality, which can feel like a profound loss.\n\n## Understanding Coercive Control: The Mechanics of Manipulation\n\nCoercive control is a pattern of behaviors aimed at dominating another person by limiting their freedom and autonomy. It is subtle, cumulative, and often hidden, making it harder to recognize than physical abuse. These behaviors include isolation from friends and family, monitoring your movements, controlling finances, gaslighting your perceptions, and instilling fear to maintain power.\n\nIn religious contexts, coercive control might look like leaders or family members using spiritual authority to silence dissent, shame you into compliance, or isolate you from outside perspectives. It’s a form of psychological abuse designed to erode your agency and enforce obedience.\n\nStudies highlight that coercive control is a significant predictor of long-term psychological harm because it attacks your sense of safety and autonomy in pervasive ways [Stark, 2007]. It’s not just about specific acts but about a continuous environment of control.\n\n## How Religious Trauma and Coercive Control Overlap\n\nIt’s important to recognize that coercive control can be a method through which religious trauma is inflicted. When religious leaders or communities use spiritual teachings to manipulate, intimidate, or isolate you, coercive control is at play. For example, demanding strict adherence to beliefs under threat of spiritual punishment while cutting you off from outside support is coercive control embedded within religious trauma.\n\nHowever, religious trauma can also arise without the presence of coercive control. You might experience trauma from internalized guilt or existential terror related to teachings without direct manipulation or control from others. Conversely, coercive control can occur in secular relationships or communities and is not exclusive to religious settings.\n\nUnderstanding the overlap helps you identify what you experienced: Was it primarily harmful religious teachings, manipulative behaviors controlling your life, or both? This clarity is crucial for seeking appropriate healing resources.\n\n## Recognizing the Signs: How to Identify Your Experience\n\nYou might feel overwhelmed, confused, or doubting your feelings. Here are some signs to help you distinguish:\n\n- **Religious trauma signs:** Intense fear of divine punishment, shame about your identity or desires, spiritual confusion, loss of faith, feeling abandoned by a higher power.\n- **Coercive control signs:** Feeling isolated from loved ones, constant surveillance or monitoring, threats or humiliation to enforce obedience, inability to make decisions without permission.\n  \nIf your experience includes ongoing psychological manipulation to restrict your choices under religious pretexts, coercive control is likely involved. If your pain centers more on internal spiritual conflict or trauma after leaving religion, religious trauma might be the core.\n\nYou may find that your experience shifts over time, and the lines blur. That’s okay. What matters most is honoring your feelings and seeking support that validates the complexity of your experience.\n\n## The Neuroscience of Trauma in These Contexts\n\nBoth religious trauma and coercive control affect your brain’s stress and attachment systems. Chronic fear and shame activate the amygdala, the brain’s alarm center, keeping you in a state of hyper-arousal or dissociation. This makes it difficult to regulate emotions, trust others, or feel grounded.\n\nCoercive control’s persistent manipulation can alter neural pathways related to decision-making and self-worth, making you doubt your reality—a phenomenon known as gaslighting [Rosenberg, 2018]. Religious trauma can similarly disrupt your internal spiritual framework, leading to existential distress and identity confusion.\n\nNeuroscientific research suggests that recovery involves re-establishing safety within your body and mind through gentle awareness practices, relational repair, and cognitive restructuring [van der Kolk, 2014]. This means your healing process will often require time and compassionate support tailored to these unique wounds.\n\n## Navigating Your Healing Process: What Helps\n\nYour healing process is deeply personal, but some approaches can support both religious trauma and coercive control recovery:\n\n- **Creating limits:** Setting clear limits on contact with people or teachings that retraumatize you helps rebuild your sense of safety.\n- **Therapeutic support:** Trauma-aware therapy, especially modalities like EMDR or somatic experiencing, can address the nervous system’s dysregulation.\n- **Community connection:** Finding supportive communities that honor your true self without judgment nurtures belonging.\n- **Rebuilding agency:** Reclaiming decision-making power in small steps restores trust in yourself.\n- **Spiritual exploration:** For some, redefining spirituality on your terms can heal spiritual wounds.\n\nRemember, healing is not linear, and setbacks are part of the process. Your feelings are valid, and your pace is sacred.\n\n## Finding Support: Who Can Help?\n\nIt can be difficult to find professionals who understand both religious trauma and coercive control. Seek therapists trained in trauma-aware care familiar with religious and psychological abuse, if possible. Support groups for survivors of religious abuse or coercive control can provide shared understanding.\n\nBooks, podcasts, and online communities can also offer validation and education. However, trust your instincts about what feels nurturing versus retraumatizing.\n\nYour healing process deserves respect, patience, and kindness—from others and from yourself.\n\n## Moving Forward with Compassion for Yourself\n\nThe path out of religious trauma and coercive control is not about rushing to \"fix\" yourself or erase the pain but about embracing your experience with compassion and curiosity. Your survival is a testament to your strength and resilience, even if it doesn’t always feel that way.\n\nYou may grieve what you lost—faith, family, certainty—and that grief is real. But you also have the capacity to create a new relationship with spirituality and self that honors your true self.\n\nYou are not alone in this. Healing is possible, and each step you take toward understanding and reclaiming your agency is a profound act of courage.\n\n\n## The Interplay Between Religious Trauma and Coercive Control: A Complex Web\n\nWhile religious trauma and coercive control can exist independently, their intersection often creates a uniquely devastating experience. Religious environments that enforce coercive control do so by weaponizing faith itself—using spiritual beliefs as tools to manipulate, intimidate, or isolate. This combination intensifies the psychological harm because it attacks not only your external freedom but also the very core of your identity and worldview.\n\nFor example, a religious community might use doctrines about obedience and sin to justify controlling behaviors, such as restricting social interactions or enforcing strict behavioral codes. This manipulation is not simply about maintaining order; it’s about consolidating power by undermining your confidence in your own judgment and feelings. When spiritual leaders or family members frame these controls as divine mandates, it becomes nearly impossible to question or resist without feeling like you are betraying your faith or loved ones.\n\nResearch in psychology highlights that this blend of control and spiritual manipulation can exacerbate symptoms of anxiety and depression, often leading to feelings of isolation and despair. Survivors report that the internal conflict between their spiritual beliefs and their lived experience of control creates profound cognitive dissonance—where their mind struggles to reconcile what they were taught with what they endured. This dissonance can make recovery feel like navigating a labyrinth with no clear exit.\n\nUnderstanding this interplay is essential because it helps clarify why leaving a controlling religious environment is not simply a matter of changing beliefs. It requires unraveling a tightly knit fabric of emotional, social, and spiritual ties that have been used to dominate and silence. Recognizing this complexity can validate your experience and emphasize that what you are facing is a multifaceted challenge, deserving of compassionate and nuanced support.\n\n## Practical Steps Toward Reclaiming Personal Autonomy Within Spiritual Contexts\n\nIf you find yourself entangled in the overlapping effects of religious trauma and coercive control, reclaiming your sense of agency can feel daunting but is achievable with intentional, grounded actions. The first step is to acknowledge the reality of the control, not as a moral failing or spiritual weakness, but as a coercive dynamic designed to diminish your freedom.\n\nBegin by gently expanding your information sources. Seek out diverse perspectives on spirituality and faith that resonate with your values and feelings rather than demanding conformity to rigid doctrines. Engaging with books, podcasts, or communities that honor questioning and doubt can create space for authentic reflection. This process helps rebuild trust in your intuition and discernment, which coercive systems often erode.\n\nNext, try to strengthen connections outside the controlling environment. Relationships that allow you to express your thoughts freely without fear of judgment can be essential for emotional recovery. Even if physical distance isn’t immediately possible, online forums or support groups with others who have experienced similar spiritual and relational control can provide validation and reduce isolation.\n\nLastly, consider developing personal rituals or practices that reconnect you with your inner sense of meaning and dignity. These need not be religious but can be simple acts — journaling, mindful breathing, nature walks — that anchor you in your own experience. Such practices gradually create a container for self-awareness and resilience, empowering you to navigate the complexities of belief and control at your own pace.\n\nEach of these steps is a reclaiming of choice, however small, and a direct counter to the erasure of self that coercive control and religious trauma inflict.\n\n## The Role of Professional Support: Finding the Right Help After Spiritual and Psychological Harm\n\nNavigating the aftermath of religious trauma intertwined with coercive control often requires support that understands the particular challenges you face. Traditional therapy models may not always account for the spiritual dimension of your distress or the subtle, pervasive nature of control you endured. Therefore, seeking professionals who are sensitive to both psychological and spiritual wounds is crucial.\n\nLook for counselors or therapists who have experience working with clients leaving high-control religious environments or who specialize in faith-related psychological distress. These professionals are more likely to appreciate the complicated feelings of loss, guilt, and confusion that arise when your spiritual community was also a source of harm. They can help you explore how your beliefs intersect with your emotional experiences without pushing you to abandon spirituality altogether unless you choose.\n\nAdditionally, group therapy or peer support groups tailored to survivors of religious coercion can provide a collective sense of validation and understanding. Hearing others articulate similar struggles often breaks through the isolation imposed by controlling systems and helps rebuild a sense of belonging that is not tied to manipulation.\n\nIt’s also important to recognize the pacing of your recovery. Healing from such layered harm is rarely linear. Compassionate professionals will honor your boundaries around discussing painful memories and support you in developing coping strategies that feel manageable. They can assist in cultivating new narratives about your spiritual identity and autonomy, helping you reclaim your story on your own terms.\n\nUltimately, the right professional support is one that meets you where you are—offering informed, respectful guidance that acknowledges both the damage inflicted and the resilience you carry within.\n\n\n## Frequently Asked Questions\n\n**1. Can religious trauma happen without coercive control?**  \nYes. Religious trauma can occur from internalized beliefs or teachings that cause deep shame or fear without direct manipulation or control by others.\n\n**2. Is coercive control always connected to physical abuse?**  \nNo. Coercive control is a form of psychological abuse that can exist independently of physical violence, often through manipulation and isolation.\n\n**3. How do I know if I am experiencing coercive control in my religious community?**  \nLook for patterns of controlling behaviors such as isolation, surveillance, threats, or demands for obedience justified by spiritual authority.\n\n**4. Can leaving a religious community stop the effects of religious trauma?**  \nLeaving may remove immediate sources of harm but does not automatically heal trauma. Emotional and spiritual wounds often require intentional healing efforts.\n\n**5. What kind of therapy helps with religious trauma and coercive control?**  \nTrauma-aware therapies such as EMDR, somatic experiencing, and cognitive-behavioral therapy tailored to your experience are often effective.\n\nYou deserve patience, kindness, and support as you navigate these complex experiences. Your truth matters, and your healing process is a sacred act of reclaiming your life. Take your time—there is no rush, only your own unfolding.",
  "tldr": [
    "Religious trauma stems from harmful experiences related to faith and spiritual beliefs, including shame, fear, and spiritual abuse.",
    "Coercive control is a pattern of manipulative behaviors intended to dominate and isolate, often used in abusive relationships, including some religious settings.",
    "While coercive control can be a component of religious trauma, not all religious trauma involves coercive control.",
    "Recognizing these distinctions can help you find the right support and strategies for your healing process."
  ],
  "faqs": [
    {
      "q": "Can religious trauma happen without coercive control?",
      "a": "Yes. Religious trauma can occur from internalized beliefs or teachings that cause deep shame or fear without direct manipulation or control by others."
    },
    {
      "q": "Is coercive control always connected to physical abuse?",
      "a": "No. Coercive control is a form of psychological abuse that can exist independently of physical violence, often through manipulation and isolation."
    },
    {
      "q": "How do I know if I am experiencing coercive control in my religious community?",
      "a": "Look for patterns of controlling behaviors such as isolation, surveillance, threats, or demands for obedience justified by spiritual authority."
    },
    {
      "q": "Can leaving a religious community stop the effects of religious trauma?",
      "a": "Leaving may remove immediate sources of harm but does not automatically heal trauma. Emotional and spiritual wounds often require intentional healing efforts."
    },
    {
      "q": "What kind of therapy helps with religious trauma and coercive control?",
      "a": "Trauma-aware therapies such as EMDR, somatic experiencing, and cognitive-behavioral therapy tailored to your experience are often effective.\n\nYou deserve patience, kindness, and support as you navigate these complex experiences. Your truth matters, and your healing process is a sacred act of reclaiming your life. Take your time—there is no rush, only your own unfolding."
    }
  ],
  "reading_time": 10,
  "word_count": 2274,
  "status": "published",
  "featured": false,
  "pub_date": "2027-07-02",
  "created_at": "2027-07-02",
  "updated_at": "2027-07-02",
  "author": "The Oracle Lover",
  "author_title": "Religious Trauma Specialist & Faith Transition Guide"
}